foy_python
