Metadata-Version: 1.0
Name: foy-python
Version: 0.0.3
Summary: Python handler for fountain-of-youth
Home-page: https://github.com/fountain-of-youth/foy-python-handler
Author: Renata Carreira
Author-email: re.carreira@gmail.com
License: LICENSE.txt
Platform: UNKNOWN
